bane/__init__.py
bane/amplifier.py
bane/bruteforcer.py
bane/ddos.py
bane/extrafun.py
bane/hasher.py
bane/info_s.py
bane/iot.py
bane/js_fuck.py
bane/pager.py
bane/payloads.py
bane/proxer.py
bane/swtch.py
bane/updating.py
bane/vulns.py
bane/wp.py
bane-4.8.6.dist-info/LICENSE
bane-4.8.6.dist-info/METADATA
bane-4.8.6.dist-info/WHEEL
bane-4.8.6.dist-info/top_level.txt
bane-4.8.6.dist-info/RECORD
