Metadata-Version: 2.1
Name: bane
Version: 4.8.6
Summary: cyber security library, penetration testing module
Home-page: https://github.com/AlaBouali/bane
Author: AlaBouali
Author-email: ala.bouali.1997@gmail.com
License: MIT License
Classifier: Programming Language :: Python
Classifier: License :: OSI Approved :: MIT License 
Requires-Python: >=2.7
License-File: LICENSE
Requires-Dist: furl
Requires-Dist: future
Requires-Dist: xtelnet
Requires-Dist: requests
Requires-Dist: PySocks
Requires-Dist: bs4
Requires-Dist: mysqlcp
Requires-Dist: kamene (==0.32)
Requires-Dist: stem
Requires-Dist: cfscrape
Requires-Dist: google
Requires-Dist: colorama
Requires-Dist: dnspython
Requires-Dist: packaging
Requires-Dist: win-inet-pton
